{
  "metadata": {
    "title": "Open Position Signal Score",
    "score_formula": "round(month_roi * 100)",
    "score_example": "10% ROI -> 10 score, 5% ROI -> 5 score",
    "generated_at": "2026-04-03 14:06:15 UTC"
  },
  "signals": [
    {
      "rank": 1,
      "coin": "HYPE",
      "long": {
        "users": 15,
        "score": 2254,
        "earliest_entry": "2026-04-03 14:00:29 UTC",
        "most_recent_entry": "2026-04-03 14:05:31 UTC"
      },
      "short": {
        "users": 8,
        "score": 877,
        "earliest_entry": "2026-04-03 14:02:20 UTC",
        "most_recent_entry": "2026-04-03 14:06:06 UTC"
      }
    },
    {
      "rank": 2,
      "coin": "BTC",
      "long": {
        "users": 18,
        "score": 13593,
        "earliest_entry": "2026-04-03 14:00:10 UTC",
        "most_recent_entry": "2026-04-03 14:05:31 UTC"
      },
      "short": {
        "users": 31,
        "score": 4967,
        "earliest_entry": "2026-04-03 14:00:26 UTC",
        "most_recent_entry": "2026-04-03 14:05:27 UTC"
      }
    },
    {
      "rank": 3,
      "coin": "ETH",
      "long": {
        "users": 6,
        "score": 701,
        "earliest_entry": "2026-04-03 14:00:49 UTC",
        "most_recent_entry": "2026-04-03 14:05:27 UTC"
      },
      "short": {
        "users": 16,
        "score": 37558,
        "earliest_entry": "2026-04-03 14:00:09 UTC",
        "most_recent_entry": "2026-04-03 14:05:27 UTC"
      }
    },
    {
      "rank": 4,
      "coin": "xyz:CL",
      "long": {
        "users": 0,
        "score": 0,
        "earliest_entry": null,
        "most_recent_entry": null
      },
      "short": {
        "users": 0,
        "score": 0,
        "earliest_entry": null,
        "most_recent_entry": null
      }
    },
    {
      "rank": 5,
      "coin": "SOL",
      "long": {
        "users": 3,
        "score": 415,
        "earliest_entry": "2026-04-03 14:01:40 UTC",
        "most_recent_entry": "2026-04-03 14:04:18 UTC"
      },
      "short": {
        "users": 9,
        "score": 1291,
        "earliest_entry": "2026-04-03 14:00:49 UTC",
        "most_recent_entry": "2026-04-03 14:05:27 UTC"
      }
    },
    {
      "rank": 6,
      "coin": "xyz:GOLD",
      "long": {
        "users": 0,
        "score": 0,
        "earliest_entry": null,
        "most_recent_entry": null
      },
      "short": {
        "users": 0,
        "score": 0,
        "earliest_entry": null,
        "most_recent_entry": null
      }
    }
  ]
}