{
  "metadata": {
    "title": "Open Position Signal Score",
    "score_formula": "round(month_roi * 100)",
    "score_example": "10% ROI -> 10 score, 5% ROI -> 5 score",
    "generated_at": "2026-04-08 10:30:59 UTC"
  },
  "signals": [
    {
      "rank": 1,
      "coin": "AAVE",
      "long": {
        "users": 7,
        "score": 670,
        "earliest_entry": "2026-04-08 10:16:38 UTC",
        "most_recent_entry": "2026-04-08 10:27:29 UTC"
      },
      "short": {
        "users": 1,
        "score": 69,
        "earliest_entry": "2026-04-08 10:24:28 UTC",
        "most_recent_entry": "2026-04-08 10:24:28 UTC"
      }
    },
    {
      "rank": 2,
      "coin": "ADA",
      "long": {
        "users": 2,
        "score": 131,
        "earliest_entry": "2026-04-08 10:21:08 UTC",
        "most_recent_entry": "2026-04-08 10:30:37 UTC"
      },
      "short": {
        "users": 4,
        "score": 276,
        "earliest_entry": "2026-04-08 10:20:23 UTC",
        "most_recent_entry": "2026-04-08 10:26:59 UTC"
      }
    },
    {
      "rank": 3,
      "coin": "AERO",
      "long": {
        "users": 0,
        "score": 0,
        "earliest_entry": null,
        "most_recent_entry": null
      },
      "short": {
        "users": 1,
        "score": 60,
        "earliest_entry": "2026-04-08 10:26:35 UTC",
        "most_recent_entry": "2026-04-08 10:26:35 UTC"
      }
    },
    {
      "rank": 4,
      "coin": "ALGO",
      "long": {
        "users": 2,
        "score": 237,
        "earliest_entry": "2026-04-08 10:17:33 UTC",
        "most_recent_entry": "2026-04-08 10:19:49 UTC"
      },
      "short": {
        "users": 5,
        "score": 382,
        "earliest_entry": "2026-04-08 10:20:00 UTC",
        "most_recent_entry": "2026-04-08 10:29:32 UTC"
      }
    },
    {
      "rank": 5,
      "coin": "APEX",
      "long": {
        "users": 1,
        "score": 45,
        "earliest_entry": "2026-04-08 10:30:37 UTC",
        "most_recent_entry": "2026-04-08 10:30:37 UTC"
      },
      "short": {
        "users": 1,
        "score": 47,
        "earliest_entry": "2026-04-08 10:29:36 UTC",
        "most_recent_entry": "2026-04-08 10:29:36 UTC"
      }
    },
    {
      "rank": 6,
      "coin": "AR",
      "long": {
        "users": 1,
        "score": 72,
        "earliest_entry": "2026-04-08 10:23:20 UTC",
        "most_recent_entry": "2026-04-08 10:23:20 UTC"
      },
      "short": {
        "users": 1,
        "score": 90,
        "earliest_entry": "2026-04-08 10:20:23 UTC",
        "most_recent_entry": "2026-04-08 10:20:23 UTC"
      }
    },
    {
      "rank": 7,
      "coin": "ARB",
      "long": {
        "users": 1,
        "score": 146,
        "earliest_entry": "2026-04-08 10:17:28 UTC",
        "most_recent_entry": "2026-04-08 10:17:28 UTC"
      },
      "short": {
        "users": 1,
        "score": 90,
        "earliest_entry": "2026-04-08 10:20:23 UTC",
        "most_recent_entry": "2026-04-08 10:20:23 UTC"
      }
    },
    {
      "rank": 8,
      "coin": "ASTER",
      "long": {
        "users": 7,
        "score": 861,
        "earliest_entry": "2026-04-08 10:15:13 UTC",
        "most_recent_entry": "2026-04-08 10:30:37 UTC"
      },
      "short": {
        "users": 2,
        "score": 211,
        "earliest_entry": "2026-04-08 10:17:15 UTC",
        "most_recent_entry": "2026-04-08 10:26:59 UTC"
      }
    },
    {
      "rank": 9,
      "coin": "ATOM",
      "long": {
        "users": 1,
        "score": 45,
        "earliest_entry": "2026-04-08 10:30:37 UTC",
        "most_recent_entry": "2026-04-08 10:30:37 UTC"
      },
      "short": {
        "users": 1,
        "score": 90,
        "earliest_entry": "2026-04-08 10:20:23 UTC",
        "most_recent_entry": "2026-04-08 10:20:23 UTC"
      }
    },
    {
      "rank": 10,
      "coin": "AVAX",
      "long": {
        "users": 2,
        "score": 98,
        "earliest_entry": "2026-04-08 10:27:50 UTC",
        "most_recent_entry": "2026-04-08 10:30:37 UTC"
      },
      "short": {
        "users": 3,
        "score": 220,
        "earliest_entry": "2026-04-08 10:20:23 UTC",
        "most_recent_entry": "2026-04-08 10:26:35 UTC"
      }
    },
    {
      "rank": 11,
      "coin": "AXS",
      "long": {
        "users": 0,
        "score": 0,
        "earliest_entry": null,
        "most_recent_entry": null
      },
      "short": {
        "users": 1,
        "score": 57,
        "earliest_entry": "2026-04-08 10:26:59 UTC",
        "most_recent_entry": "2026-04-08 10:26:59 UTC"
      }
    },
    {
      "rank": 12,
      "coin": "AZTEC",
      "long": {
        "users": 0,
        "score": 0,
        "earliest_entry": null,
        "most_recent_entry": null
      },
      "short": {
        "users": 1,
        "score": 90,
        "earliest_entry": "2026-04-08 10:20:23 UTC",
        "most_recent_entry": "2026-04-08 10:20:23 UTC"
      }
    },
    {
      "rank": 13,
      "coin": "BCH",
      "long": {
        "users": 3,
        "score": 368,
        "earliest_entry": "2026-04-08 10:16:35 UTC",
        "most_recent_entry": "2026-04-08 10:24:28 UTC"
      },
      "short": {
        "users": 0,
        "score": 0,
        "earliest_entry": null,
        "most_recent_entry": null
      }
    },
    {
      "rank": 14,
      "coin": "BERA",
      "long": {
        "users": 1,
        "score": 93,
        "earliest_entry": "2026-04-08 10:20:00 UTC",
        "most_recent_entry": "2026-04-08 10:20:00 UTC"
      },
      "short": {
        "users": 3,
        "score": 207,
        "earliest_entry": "2026-04-08 10:20:23 UTC",
        "most_recent_entry": "2026-04-08 10:26:59 UTC"
      }
    },
    {
      "rank": 15,
      "coin": "BNB",
      "long": {
        "users": 1,
        "score": 100,
        "earliest_entry": "2026-04-08 10:19:38 UTC",
        "most_recent_entry": "2026-04-08 10:19:38 UTC"
      },
      "short": {
        "users": 0,
        "score": 0,
        "earliest_entry": null,
        "most_recent_entry": null
      }
    },
    {
      "rank": 16,
      "coin": "BTC",
      "long": {
        "users": 105,
        "score": 28940,
        "earliest_entry": "2026-04-08 10:14:45 UTC",
        "most_recent_entry": "2026-04-08 10:30:37 UTC"
      },
      "short": {
        "users": 45,
        "score": 6377,
        "earliest_entry": "2026-04-08 10:14:51 UTC",
        "most_recent_entry": "2026-04-08 10:30:38 UTC"
      }
    },
    {
      "rank": 17,
      "coin": "CC",
      "long": {
        "users": 1,
        "score": 46,
        "earliest_entry": "2026-04-08 10:30:09 UTC",
        "most_recent_entry": "2026-04-08 10:30:09 UTC"
      },
      "short": {
        "users": 1,
        "score": 90,
        "earliest_entry": "2026-04-08 10:20:23 UTC",
        "most_recent_entry": "2026-04-08 10:20:23 UTC"
      }
    },
    {
      "rank": 18,
      "coin": "CELO",
      "long": {
        "users": 0,
        "score": 0,
        "earliest_entry": null,
        "most_recent_entry": null
      },
      "short": {
        "users": 2,
        "score": 136,
        "earliest_entry": "2026-04-08 10:20:23 UTC",
        "most_recent_entry": "2026-04-08 10:30:09 UTC"
      }
    },
    {
      "rank": 19,
      "coin": "CFX",
      "long": {
        "users": 1,
        "score": 45,
        "earliest_entry": "2026-04-08 10:30:37 UTC",
        "most_recent_entry": "2026-04-08 10:30:37 UTC"
      },
      "short": {
        "users": 0,
        "score": 0,
        "earliest_entry": null,
        "most_recent_entry": null
      }
    },
    {
      "rank": 20,
      "coin": "CHILLGUY",
      "long": {
        "users": 1,
        "score": 95,
        "earliest_entry": "2026-04-08 10:19:49 UTC",
        "most_recent_entry": "2026-04-08 10:19:49 UTC"
      },
      "short": {
        "users": 0,
        "score": 0,
        "earliest_entry": null,
        "most_recent_entry": null
      }
    },
    {
      "rank": 21,
      "coin": "COMP",
      "long": {
        "users": 1,
        "score": 95,
        "earliest_entry": "2026-04-08 10:19:50 UTC",
        "most_recent_entry": "2026-04-08 10:19:50 UTC"
      },
      "short": {
        "users": 0,
        "score": 0,
        "earliest_entry": null,
        "most_recent_entry": null
      }
    },
    {
      "rank": 22,
      "coin": "CRV",
      "long": {
        "users": 4,
        "score": 298,
        "earliest_entry": "2026-04-08 10:19:50 UTC",
        "most_recent_entry": "2026-04-08 10:27:19 UTC"
      },
      "short": {
        "users": 2,
        "score": 147,
        "earliest_entry": "2026-04-08 10:20:23 UTC",
        "most_recent_entry": "2026-04-08 10:26:59 UTC"
      }
    },
    {
      "rank": 23,
      "coin": "DOGE",
      "long": {
        "users": 8,
        "score": 511,
        "earliest_entry": "2026-04-08 10:18:16 UTC",
        "most_recent_entry": "2026-04-08 10:30:37 UTC"
      },
      "short": {
        "users": 2,
        "score": 126,
        "earliest_entry": "2026-04-08 10:24:28 UTC",
        "most_recent_entry": "2026-04-08 10:26:59 UTC"
      }
    },
    {
      "rank": 24,
      "coin": "DOT",
      "long": {
        "users": 5,
        "score": 770,
        "earliest_entry": "2026-04-08 10:15:18 UTC",
        "most_recent_entry": "2026-04-08 10:24:29 UTC"
      },
      "short": {
        "users": 3,
        "score": 226,
        "earliest_entry": "2026-04-08 10:20:23 UTC",
        "most_recent_entry": "2026-04-08 10:26:35 UTC"
      }
    },
    {
      "rank": 25,
      "coin": "EIGEN",
      "long": {
        "users": 1,
        "score": 69,
        "earliest_entry": "2026-04-08 10:24:31 UTC",
        "most_recent_entry": "2026-04-08 10:24:31 UTC"
      },
      "short": {
        "users": 1,
        "score": 46,
        "earliest_entry": "2026-04-08 10:30:09 UTC",
        "most_recent_entry": "2026-04-08 10:30:09 UTC"
      }
    },
    {
      "rank": 26,
      "coin": "ENA",
      "long": {
        "users": 12,
        "score": 1090,
        "earliest_entry": "2026-04-08 10:17:13 UTC",
        "most_recent_entry": "2026-04-08 10:30:37 UTC"
      },
      "short": {
        "users": 0,
        "score": 0,
        "earliest_entry": null,
        "most_recent_entry": null
      }
    },
    {
      "rank": 27,
      "coin": "ENS",
      "long": {
        "users": 1,
        "score": 45,
        "earliest_entry": "2026-04-08 10:30:37 UTC",
        "most_recent_entry": "2026-04-08 10:30:37 UTC"
      },
      "short": {
        "users": 1,
        "score": 90,
        "earliest_entry": "2026-04-08 10:20:23 UTC",
        "most_recent_entry": "2026-04-08 10:20:23 UTC"
      }
    },
    {
      "rank": 28,
      "coin": "ETC",
      "long": {
        "users": 0,
        "score": 0,
        "earliest_entry": null,
        "most_recent_entry": null
      },
      "short": {
        "users": 2,
        "score": 147,
        "earliest_entry": "2026-04-08 10:20:23 UTC",
        "most_recent_entry": "2026-04-08 10:26:59 UTC"
      }
    },
    {
      "rank": 29,
      "coin": "ETH",
      "long": {
        "users": 72,
        "score": 8278,
        "earliest_entry": "2026-04-08 10:14:50 UTC",
        "most_recent_entry": "2026-04-08 10:30:37 UTC"
      },
      "short": {
        "users": 18,
        "score": 2610,
        "earliest_entry": "2026-04-08 10:14:51 UTC",
        "most_recent_entry": "2026-04-08 10:30:15 UTC"
      }
    },
    {
      "rank": 30,
      "coin": "ETHFI",
      "long": {
        "users": 2,
        "score": 976,
        "earliest_entry": "2026-04-08 10:14:53 UTC",
        "most_recent_entry": "2026-04-08 10:22:20 UTC"
      },
      "short": {
        "users": 2,
        "score": 181,
        "earliest_entry": "2026-04-08 10:20:10 UTC",
        "most_recent_entry": "2026-04-08 10:20:23 UTC"
      }
    },
    {
      "rank": 31,
      "coin": "FARTCOIN",
      "long": {
        "users": 15,
        "score": 1151,
        "earliest_entry": "2026-04-08 10:17:15 UTC",
        "most_recent_entry": "2026-04-08 10:30:37 UTC"
      },
      "short": {
        "users": 6,
        "score": 382,
        "earliest_entry": "2026-04-08 10:19:18 UTC",
        "most_recent_entry": "2026-04-08 10:29:32 UTC"
      }
    },
    {
      "rank": 32,
      "coin": "FET",
      "long": {
        "users": 0,
        "score": 0,
        "earliest_entry": null,
        "most_recent_entry": null
      },
      "short": {
        "users": 1,
        "score": 90,
        "earliest_entry": "2026-04-08 10:20:23 UTC",
        "most_recent_entry": "2026-04-08 10:20:23 UTC"
      }
    },
    {
      "rank": 33,
      "coin": "FIL",
      "long": {
        "users": 5,
        "score": 885,
        "earliest_entry": "2026-04-08 10:15:18 UTC",
        "most_recent_entry": "2026-04-08 10:24:38 UTC"
      },
      "short": {
        "users": 1,
        "score": 90,
        "earliest_entry": "2026-04-08 10:20:23 UTC",
        "most_recent_entry": "2026-04-08 10:20:23 UTC"
      }
    },
    {
      "rank": 34,
      "coin": "FTT",
      "long": {
        "users": 1,
        "score": 46,
        "earliest_entry": "2026-04-08 10:30:12 UTC",
        "most_recent_entry": "2026-04-08 10:30:12 UTC"
      },
      "short": {
        "users": 0,
        "score": 0,
        "earliest_entry": null,
        "most_recent_entry": null
      }
    },
    {
      "rank": 35,
      "coin": "GALA",
      "long": {
        "users": 0,
        "score": 0,
        "earliest_entry": null,
        "most_recent_entry": null
      },
      "short": {
        "users": 1,
        "score": 57,
        "earliest_entry": "2026-04-08 10:26:59 UTC",
        "most_recent_entry": "2026-04-08 10:26:59 UTC"
      }
    },
    {
      "rank": 36,
      "coin": "GMX",
      "long": {
        "users": 1,
        "score": 79,
        "earliest_entry": "2026-04-08 10:21:48 UTC",
        "most_recent_entry": "2026-04-08 10:21:48 UTC"
      },
      "short": {
        "users": 0,
        "score": 0,
        "earliest_entry": null,
        "most_recent_entry": null
      }
    },
    {
      "rank": 37,
      "coin": "GOAT",
      "long": {
        "users": 1,
        "score": 47,
        "earliest_entry": "2026-04-08 10:29:38 UTC",
        "most_recent_entry": "2026-04-08 10:29:38 UTC"
      },
      "short": {
        "users": 0,
        "score": 0,
        "earliest_entry": null,
        "most_recent_entry": null
      }
    },
    {
      "rank": 38,
      "coin": "GRASS",
      "long": {
        "users": 3,
        "score": 219,
        "earliest_entry": "2026-04-08 10:22:20 UTC",
        "most_recent_entry": "2026-04-08 10:24:18 UTC"
      },
      "short": {
        "users": 1,
        "score": 90,
        "earliest_entry": "2026-04-08 10:20:23 UTC",
        "most_recent_entry": "2026-04-08 10:20:23 UTC"
      }
    },
    {
      "rank": 39,
      "coin": "GRIFFAIN",
      "long": {
        "users": 2,
        "score": 206,
        "earliest_entry": "2026-04-08 10:18:56 UTC",
        "most_recent_entry": "2026-04-08 10:19:49 UTC"
      },
      "short": {
        "users": 1,
        "score": 90,
        "earliest_entry": "2026-04-08 10:20:23 UTC",
        "most_recent_entry": "2026-04-08 10:20:23 UTC"
      }
    },
    {
      "rank": 40,
      "coin": "HBAR",
      "long": {
        "users": 2,
        "score": 117,
        "earliest_entry": "2026-04-08 10:23:20 UTC",
        "most_recent_entry": "2026-04-08 10:30:37 UTC"
      },
      "short": {
        "users": 0,
        "score": 0,
        "earliest_entry": null,
        "most_recent_entry": null
      }
    },
    {
      "rank": 41,
      "coin": "HEMI",
      "long": {
        "users": 0,
        "score": 0,
        "earliest_entry": null,
        "most_recent_entry": null
      },
      "short": {
        "users": 1,
        "score": 90,
        "earliest_entry": "2026-04-08 10:20:23 UTC",
        "most_recent_entry": "2026-04-08 10:20:23 UTC"
      }
    },
    {
      "rank": 42,
      "coin": "HYPE",
      "long": {
        "users": 110,
        "score": 10694,
        "earliest_entry": "2026-04-08 10:14:58 UTC",
        "most_recent_entry": "2026-04-08 10:30:37 UTC"
      },
      "short": {
        "users": 19,
        "score": 1819,
        "earliest_entry": "2026-04-08 10:16:17 UTC",
        "most_recent_entry": "2026-04-08 10:30:15 UTC"
      }
    },
    {
      "rank": 43,
      "coin": "ICP",
      "long": {
        "users": 2,
        "score": 135,
        "earliest_entry": "2026-04-08 10:20:12 UTC",
        "most_recent_entry": "2026-04-08 10:30:37 UTC"
      },
      "short": {
        "users": 0,
        "score": 0,
        "earliest_entry": null,
        "most_recent_entry": null
      }
    },
    {
      "rank": 44,
      "coin": "IP",
      "long": {
        "users": 0,
        "score": 0,
        "earliest_entry": null,
        "most_recent_entry": null
      },
      "short": {
        "users": 1,
        "score": 70,
        "earliest_entry": "2026-04-08 10:24:23 UTC",
        "most_recent_entry": "2026-04-08 10:24:23 UTC"
      }
    },
    {
      "rank": 45,
      "coin": "JUP",
      "long": {
        "users": 3,
        "score": 202,
        "earliest_entry": "2026-04-08 10:20:23 UTC",
        "most_recent_entry": "2026-04-08 10:30:37 UTC"
      },
      "short": {
        "users": 0,
        "score": 0,
        "earliest_entry": null,
        "most_recent_entry": null
      }
    },
    {
      "rank": 46,
      "coin": "LDO",
      "long": {
        "users": 2,
        "score": 144,
        "earliest_entry": "2026-04-08 10:19:50 UTC",
        "most_recent_entry": "2026-04-08 10:28:32 UTC"
      },
      "short": {
        "users": 0,
        "score": 0,
        "earliest_entry": null,
        "most_recent_entry": null
      }
    },
    {
      "rank": 47,
      "coin": "LINEA",
      "long": {
        "users": 1,
        "score": 45,
        "earliest_entry": "2026-04-08 10:30:37 UTC",
        "most_recent_entry": "2026-04-08 10:30:37 UTC"
      },
      "short": {
        "users": 2,
        "score": 145,
        "earliest_entry": "2026-04-08 10:20:23 UTC",
        "most_recent_entry": "2026-04-08 10:27:28 UTC"
      }
    },
    {
      "rank": 48,
      "coin": "LINK",
      "long": {
        "users": 10,
        "score": 865,
        "earliest_entry": "2026-04-08 10:15:40 UTC",
        "most_recent_entry": "2026-04-08 10:30:37 UTC"
      },
      "short": {
        "users": 1,
        "score": 90,
        "earliest_entry": "2026-04-08 10:20:23 UTC",
        "most_recent_entry": "2026-04-08 10:20:23 UTC"
      }
    },
    {
      "rank": 49,
      "coin": "LIT",
      "long": {
        "users": 22,
        "score": 1919,
        "earliest_entry": "2026-04-08 10:15:34 UTC",
        "most_recent_entry": "2026-04-08 10:30:37 UTC"
      },
      "short": {
        "users": 5,
        "score": 504,
        "earliest_entry": "2026-04-08 10:15:32 UTC",
        "most_recent_entry": "2026-04-08 10:29:36 UTC"
      }
    },
    {
      "rank": 50,
      "coin": "LTC",
      "long": {
        "users": 3,
        "score": 315,
        "earliest_entry": "2026-04-08 10:16:07 UTC",
        "most_recent_entry": "2026-04-08 10:30:37 UTC"
      },
      "short": {
        "users": 0,
        "score": 0,
        "earliest_entry": null,
        "most_recent_entry": null
      }
    },
    {
      "rank": 51,
      "coin": "MEGA",
      "long": {
        "users": 0,
        "score": 0,
        "earliest_entry": null,
        "most_recent_entry": null
      },
      "short": {
        "users": 1,
        "score": 90,
        "earliest_entry": "2026-04-08 10:20:23 UTC",
        "most_recent_entry": "2026-04-08 10:20:23 UTC"
      }
    },
    {
      "rank": 52,
      "coin": "MELANIA",
      "long": {
        "users": 0,
        "score": 0,
        "earliest_entry": null,
        "most_recent_entry": null
      },
      "short": {
        "users": 2,
        "score": 147,
        "earliest_entry": "2026-04-08 10:20:23 UTC",
        "most_recent_entry": "2026-04-08 10:26:59 UTC"
      }
    },
    {
      "rank": 53,
      "coin": "MEME",
      "long": {
        "users": 1,
        "score": 77,
        "earliest_entry": "2026-04-08 10:22:20 UTC",
        "most_recent_entry": "2026-04-08 10:22:20 UTC"
      },
      "short": {
        "users": 0,
        "score": 0,
        "earliest_entry": null,
        "most_recent_entry": null
      }
    },
    {
      "rank": 54,
      "coin": "MET",
      "long": {
        "users": 1,
        "score": 59,
        "earliest_entry": "2026-04-08 10:26:44 UTC",
        "most_recent_entry": "2026-04-08 10:26:44 UTC"
      },
      "short": {
        "users": 0,
        "score": 0,
        "earliest_entry": null,
        "most_recent_entry": null
      }
    },
    {
      "rank": 55,
      "coin": "MNT",
      "long": {
        "users": 3,
        "score": 152,
        "earliest_entry": "2026-04-08 10:27:28 UTC",
        "most_recent_entry": "2026-04-08 10:30:37 UTC"
      },
      "short": {
        "users": 1,
        "score": 90,
        "earliest_entry": "2026-04-08 10:20:23 UTC",
        "most_recent_entry": "2026-04-08 10:20:23 UTC"
      }
    },
    {
      "rank": 56,
      "coin": "MON",
      "long": {
        "users": 13,
        "score": 20026,
        "earliest_entry": "2026-04-08 10:14:45 UTC",
        "most_recent_entry": "2026-04-08 10:29:38 UTC"
      },
      "short": {
        "users": 3,
        "score": 376,
        "earliest_entry": "2026-04-08 10:16:19 UTC",
        "most_recent_entry": "2026-04-08 10:20:23 UTC"
      }
    },
    {
      "rank": 57,
      "coin": "MOODENG",
      "long": {
        "users": 3,
        "score": 266,
        "earliest_entry": "2026-04-08 10:19:49 UTC",
        "most_recent_entry": "2026-04-08 10:22:26 UTC"
      },
      "short": {
        "users": 1,
        "score": 57,
        "earliest_entry": "2026-04-08 10:26:59 UTC",
        "most_recent_entry": "2026-04-08 10:26:59 UTC"
      }
    },
    {
      "rank": 58,
      "coin": "MORPHO",
      "long": {
        "users": 3,
        "score": 392,
        "earliest_entry": "2026-04-08 10:15:21 UTC",
        "most_recent_entry": "2026-04-08 10:26:59 UTC"
      },
      "short": {
        "users": 1,
        "score": 90,
        "earliest_entry": "2026-04-08 10:20:23 UTC",
        "most_recent_entry": "2026-04-08 10:20:23 UTC"
      }
    },
    {
      "rank": 59,
      "coin": "NEAR",
      "long": {
        "users": 12,
        "score": 1199,
        "earliest_entry": "2026-04-08 10:16:33 UTC",
        "most_recent_entry": "2026-04-08 10:30:37 UTC"
      },
      "short": {
        "users": 1,
        "score": 90,
        "earliest_entry": "2026-04-08 10:20:23 UTC",
        "most_recent_entry": "2026-04-08 10:20:23 UTC"
      }
    },
    {
      "rank": 60,
      "coin": "NIL",
      "long": {
        "users": 0,
        "score": 0,
        "earliest_entry": null,
        "most_recent_entry": null
      },
      "short": {
        "users": 1,
        "score": 90,
        "earliest_entry": "2026-04-08 10:20:23 UTC",
        "most_recent_entry": "2026-04-08 10:20:23 UTC"
      }
    },
    {
      "rank": 61,
      "coin": "ONDO",
      "long": {
        "users": 4,
        "score": 282,
        "earliest_entry": "2026-04-08 10:19:08 UTC",
        "most_recent_entry": "2026-04-08 10:27:13 UTC"
      },
      "short": {
        "users": 0,
        "score": 0,
        "earliest_entry": null,
        "most_recent_entry": null
      }
    },
    {
      "rank": 62,
      "coin": "OP",
      "long": {
        "users": 0,
        "score": 0,
        "earliest_entry": null,
        "most_recent_entry": null
      },
      "short": {
        "users": 2,
        "score": 147,
        "earliest_entry": "2026-04-08 10:20:23 UTC",
        "most_recent_entry": "2026-04-08 10:26:59 UTC"
      }
    },
    {
      "rank": 63,
      "coin": "PAXG",
      "long": {
        "users": 4,
        "score": 237,
        "earliest_entry": "2026-04-08 10:19:40 UTC",
        "most_recent_entry": "2026-04-08 10:30:37 UTC"
      },
      "short": {
        "users": 1,
        "score": 123,
        "earliest_entry": "2026-04-08 10:18:23 UTC",
        "most_recent_entry": "2026-04-08 10:18:23 UTC"
      }
    },
    {
      "rank": 64,
      "coin": "PENDLE",
      "long": {
        "users": 1,
        "score": 60,
        "earliest_entry": "2026-04-08 10:26:35 UTC",
        "most_recent_entry": "2026-04-08 10:26:35 UTC"
      },
      "short": {
        "users": 0,
        "score": 0,
        "earliest_entry": null,
        "most_recent_entry": null
      }
    },
    {
      "rank": 65,
      "coin": "PENGU",
      "long": {
        "users": 1,
        "score": 67,
        "earliest_entry": "2026-04-08 10:24:43 UTC",
        "most_recent_entry": "2026-04-08 10:24:43 UTC"
      },
      "short": {
        "users": 1,
        "score": 69,
        "earliest_entry": "2026-04-08 10:24:29 UTC",
        "most_recent_entry": "2026-04-08 10:24:29 UTC"
      }
    },
    {
      "rank": 66,
      "coin": "PNUT",
      "long": {
        "users": 1,
        "score": 95,
        "earliest_entry": "2026-04-08 10:19:49 UTC",
        "most_recent_entry": "2026-04-08 10:19:49 UTC"
      },
      "short": {
        "users": 0,
        "score": 0,
        "earliest_entry": null,
        "most_recent_entry": null
      }
    },
    {
      "rank": 67,
      "coin": "POL",
      "long": {
        "users": 1,
        "score": 72,
        "earliest_entry": "2026-04-08 10:23:20 UTC",
        "most_recent_entry": "2026-04-08 10:23:20 UTC"
      },
      "short": {
        "users": 1,
        "score": 90,
        "earliest_entry": "2026-04-08 10:20:23 UTC",
        "most_recent_entry": "2026-04-08 10:20:23 UTC"
      }
    },
    {
      "rank": 68,
      "coin": "POPCAT",
      "long": {
        "users": 1,
        "score": 45,
        "earliest_entry": "2026-04-08 10:30:37 UTC",
        "most_recent_entry": "2026-04-08 10:30:37 UTC"
      },
      "short": {
        "users": 0,
        "score": 0,
        "earliest_entry": null,
        "most_recent_entry": null
      }
    },
    {
      "rank": 69,
      "coin": "PUMP",
      "long": {
        "users": 12,
        "score": 1037,
        "earliest_entry": "2026-04-08 10:16:27 UTC",
        "most_recent_entry": "2026-04-08 10:30:37 UTC"
      },
      "short": {
        "users": 0,
        "score": 0,
        "earliest_entry": null,
        "most_recent_entry": null
      }
    },
    {
      "rank": 70,
      "coin": "PURR",
      "long": {
        "users": 2,
        "score": 120,
        "earliest_entry": "2026-04-08 10:23:20 UTC",
        "most_recent_entry": "2026-04-08 10:29:07 UTC"
      },
      "short": {
        "users": 2,
        "score": 109,
        "earliest_entry": "2026-04-08 10:26:33 UTC",
        "most_recent_entry": "2026-04-08 10:29:02 UTC"
      }
    },
    {
      "rank": 71,
      "coin": "RENDER",
      "long": {
        "users": 6,
        "score": 651,
        "earliest_entry": "2026-04-08 10:15:40 UTC",
        "most_recent_entry": "2026-04-08 10:29:07 UTC"
      },
      "short": {
        "users": 1,
        "score": 90,
        "earliest_entry": "2026-04-08 10:20:23 UTC",
        "most_recent_entry": "2026-04-08 10:20:23 UTC"
      }
    },
    {
      "rank": 72,
      "coin": "RESOLV",
      "long": {
        "users": 2,
        "score": 138,
        "earliest_entry": "2026-04-08 10:20:00 UTC",
        "most_recent_entry": "2026-04-08 10:30:37 UTC"
      },
      "short": {
        "users": 0,
        "score": 0,
        "earliest_entry": null,
        "most_recent_entry": null
      }
    },
    {
      "rank": 73,
      "coin": "REZ",
      "long": {
        "users": 1,
        "score": 48,
        "earliest_entry": "2026-04-08 10:29:05 UTC",
        "most_recent_entry": "2026-04-08 10:29:05 UTC"
      },
      "short": {
        "users": 0,
        "score": 0,
        "earliest_entry": null,
        "most_recent_entry": null
      }
    },
    {
      "rank": 74,
      "coin": "RSR",
      "long": {
        "users": 0,
        "score": 0,
        "earliest_entry": null,
        "most_recent_entry": null
      },
      "short": {
        "users": 1,
        "score": 90,
        "earliest_entry": "2026-04-08 10:20:23 UTC",
        "most_recent_entry": "2026-04-08 10:20:23 UTC"
      }
    },
    {
      "rank": 75,
      "coin": "RUNE",
      "long": {
        "users": 1,
        "score": 53,
        "earliest_entry": "2026-04-08 10:27:43 UTC",
        "most_recent_entry": "2026-04-08 10:27:43 UTC"
      },
      "short": {
        "users": 0,
        "score": 0,
        "earliest_entry": null,
        "most_recent_entry": null
      }
    },
    {
      "rank": 76,
      "coin": "SAND",
      "long": {
        "users": 0,
        "score": 0,
        "earliest_entry": null,
        "most_recent_entry": null
      },
      "short": {
        "users": 1,
        "score": 90,
        "earliest_entry": "2026-04-08 10:20:23 UTC",
        "most_recent_entry": "2026-04-08 10:20:23 UTC"
      }
    },
    {
      "rank": 77,
      "coin": "SEI",
      "long": {
        "users": 0,
        "score": 0,
        "earliest_entry": null,
        "most_recent_entry": null
      },
      "short": {
        "users": 1,
        "score": 57,
        "earliest_entry": "2026-04-08 10:26:59 UTC",
        "most_recent_entry": "2026-04-08 10:26:59 UTC"
      }
    },
    {
      "rank": 78,
      "coin": "SKR",
      "long": {
        "users": 0,
        "score": 0,
        "earliest_entry": null,
        "most_recent_entry": null
      },
      "short": {
        "users": 1,
        "score": 90,
        "earliest_entry": "2026-04-08 10:20:23 UTC",
        "most_recent_entry": "2026-04-08 10:20:23 UTC"
      }
    },
    {
      "rank": 79,
      "coin": "SKY",
      "long": {
        "users": 1,
        "score": 899,
        "earliest_entry": "2026-04-08 10:14:53 UTC",
        "most_recent_entry": "2026-04-08 10:14:53 UTC"
      },
      "short": {
        "users": 0,
        "score": 0,
        "earliest_entry": null,
        "most_recent_entry": null
      }
    },
    {
      "rank": 80,
      "coin": "SOL",
      "long": {
        "users": 37,
        "score": 3727,
        "earliest_entry": "2026-04-08 10:14:59 UTC",
        "most_recent_entry": "2026-04-08 10:30:37 UTC"
      },
      "short": {
        "users": 10,
        "score": 1292,
        "earliest_entry": "2026-04-08 10:15:02 UTC",
        "most_recent_entry": "2026-04-08 10:30:17 UTC"
      }
    },
    {
      "rank": 81,
      "coin": "SPX",
      "long": {
        "users": 1,
        "score": 127,
        "earliest_entry": "2026-04-08 10:18:16 UTC",
        "most_recent_entry": "2026-04-08 10:18:16 UTC"
      },
      "short": {
        "users": 0,
        "score": 0,
        "earliest_entry": null,
        "most_recent_entry": null
      }
    },
    {
      "rank": 82,
      "coin": "STABLE",
      "long": {
        "users": 3,
        "score": 286,
        "earliest_entry": "2026-04-08 10:19:15 UTC",
        "most_recent_entry": "2026-04-08 10:23:13 UTC"
      },
      "short": {
        "users": 1,
        "score": 93,
        "earliest_entry": "2026-04-08 10:20:00 UTC",
        "most_recent_entry": "2026-04-08 10:20:00 UTC"
      }
    },
    {
      "rank": 83,
      "coin": "STRK",
      "long": {
        "users": 2,
        "score": 98,
        "earliest_entry": "2026-04-08 10:27:50 UTC",
        "most_recent_entry": "2026-04-08 10:30:37 UTC"
      },
      "short": {
        "users": 1,
        "score": 57,
        "earliest_entry": "2026-04-08 10:26:59 UTC",
        "most_recent_entry": "2026-04-08 10:26:59 UTC"
      }
    },
    {
      "rank": 84,
      "coin": "STX",
      "long": {
        "users": 0,
        "score": 0,
        "earliest_entry": null,
        "most_recent_entry": null
      },
      "short": {
        "users": 1,
        "score": 90,
        "earliest_entry": "2026-04-08 10:20:23 UTC",
        "most_recent_entry": "2026-04-08 10:20:23 UTC"
      }
    },
    {
      "rank": 85,
      "coin": "SUI",
      "long": {
        "users": 7,
        "score": 545,
        "earliest_entry": "2026-04-08 10:16:34 UTC",
        "most_recent_entry": "2026-04-08 10:30:37 UTC"
      },
      "short": {
        "users": 2,
        "score": 195,
        "earliest_entry": "2026-04-08 10:19:18 UTC",
        "most_recent_entry": "2026-04-08 10:20:23 UTC"
      }
    },
    {
      "rank": 86,
      "coin": "SYRUP",
      "long": {
        "users": 1,
        "score": 77,
        "earliest_entry": "2026-04-08 10:22:12 UTC",
        "most_recent_entry": "2026-04-08 10:22:12 UTC"
      },
      "short": {
        "users": 0,
        "score": 0,
        "earliest_entry": null,
        "most_recent_entry": null
      }
    },
    {
      "rank": 87,
      "coin": "TAO",
      "long": {
        "users": 42,
        "score": 5687,
        "earliest_entry": "2026-04-08 10:15:00 UTC",
        "most_recent_entry": "2026-04-08 10:30:37 UTC"
      },
      "short": {
        "users": 4,
        "score": 291,
        "earliest_entry": "2026-04-08 10:18:09 UTC",
        "most_recent_entry": "2026-04-08 10:28:31 UTC"
      }
    },
    {
      "rank": 88,
      "coin": "TIA",
      "long": {
        "users": 1,
        "score": 77,
        "earliest_entry": "2026-04-08 10:22:20 UTC",
        "most_recent_entry": "2026-04-08 10:22:20 UTC"
      },
      "short": {
        "users": 1,
        "score": 57,
        "earliest_entry": "2026-04-08 10:26:59 UTC",
        "most_recent_entry": "2026-04-08 10:26:59 UTC"
      }
    },
    {
      "rank": 89,
      "coin": "TON",
      "long": {
        "users": 5,
        "score": 749,
        "earliest_entry": "2026-04-08 10:15:18 UTC",
        "most_recent_entry": "2026-04-08 10:30:37 UTC"
      },
      "short": {
        "users": 0,
        "score": 0,
        "earliest_entry": null,
        "most_recent_entry": null
      }
    },
    {
      "rank": 90,
      "coin": "TRUMP",
      "long": {
        "users": 1,
        "score": 146,
        "earliest_entry": "2026-04-08 10:17:24 UTC",
        "most_recent_entry": "2026-04-08 10:17:24 UTC"
      },
      "short": {
        "users": 3,
        "score": 301,
        "earliest_entry": "2026-04-08 10:17:15 UTC",
        "most_recent_entry": "2026-04-08 10:26:59 UTC"
      }
    },
    {
      "rank": 91,
      "coin": "TURBO",
      "long": {
        "users": 1,
        "score": 76,
        "earliest_entry": "2026-04-08 10:22:26 UTC",
        "most_recent_entry": "2026-04-08 10:22:26 UTC"
      },
      "short": {
        "users": 0,
        "score": 0,
        "earliest_entry": null,
        "most_recent_entry": null
      }
    },
    {
      "rank": 92,
      "coin": "UNI",
      "long": {
        "users": 4,
        "score": 317,
        "earliest_entry": "2026-04-08 10:19:38 UTC",
        "most_recent_entry": "2026-04-08 10:27:43 UTC"
      },
      "short": {
        "users": 1,
        "score": 57,
        "earliest_entry": "2026-04-08 10:26:59 UTC",
        "most_recent_entry": "2026-04-08 10:26:59 UTC"
      }
    },
    {
      "rank": 93,
      "coin": "VIRTUAL",
      "long": {
        "users": 3,
        "score": 408,
        "earliest_entry": "2026-04-08 10:17:15 UTC",
        "most_recent_entry": "2026-04-08 10:19:15 UTC"
      },
      "short": {
        "users": 0,
        "score": 0,
        "earliest_entry": null,
        "most_recent_entry": null
      }
    },
    {
      "rank": 94,
      "coin": "VVV",
      "long": {
        "users": 16,
        "score": 1548,
        "earliest_entry": "2026-04-08 10:16:35 UTC",
        "most_recent_entry": "2026-04-08 10:29:09 UTC"
      },
      "short": {
        "users": 0,
        "score": 0,
        "earliest_entry": null,
        "most_recent_entry": null
      }
    },
    {
      "rank": 95,
      "coin": "W",
      "long": {
        "users": 0,
        "score": 0,
        "earliest_entry": null,
        "most_recent_entry": null
      },
      "short": {
        "users": 1,
        "score": 90,
        "earliest_entry": "2026-04-08 10:20:23 UTC",
        "most_recent_entry": "2026-04-08 10:20:23 UTC"
      }
    },
    {
      "rank": 96,
      "coin": "WIF",
      "long": {
        "users": 5,
        "score": 480,
        "earliest_entry": "2026-04-08 10:15:40 UTC",
        "most_recent_entry": "2026-04-08 10:30:37 UTC"
      },
      "short": {
        "users": 0,
        "score": 0,
        "earliest_entry": null,
        "most_recent_entry": null
      }
    },
    {
      "rank": 97,
      "coin": "WLD",
      "long": {
        "users": 4,
        "score": 210,
        "earliest_entry": "2026-04-08 10:24:29 UTC",
        "most_recent_entry": "2026-04-08 10:30:37 UTC"
      },
      "short": {
        "users": 1,
        "score": 60,
        "earliest_entry": "2026-04-08 10:26:35 UTC",
        "most_recent_entry": "2026-04-08 10:26:35 UTC"
      }
    },
    {
      "rank": 98,
      "coin": "WLFI",
      "long": {
        "users": 2,
        "score": 159,
        "earliest_entry": "2026-04-08 10:19:21 UTC",
        "most_recent_entry": "2026-04-08 10:27:13 UTC"
      },
      "short": {
        "users": 0,
        "score": 0,
        "earliest_entry": null,
        "most_recent_entry": null
      }
    },
    {
      "rank": 99,
      "coin": "XLM",
      "long": {
        "users": 1,
        "score": 127,
        "earliest_entry": "2026-04-08 10:18:16 UTC",
        "most_recent_entry": "2026-04-08 10:18:16 UTC"
      },
      "short": {
        "users": 1,
        "score": 46,
        "earliest_entry": "2026-04-08 10:30:09 UTC",
        "most_recent_entry": "2026-04-08 10:30:09 UTC"
      }
    },
    {
      "rank": 100,
      "coin": "XMR",
      "long": {
        "users": 6,
        "score": 492,
        "earliest_entry": "2026-04-08 10:16:35 UTC",
        "most_recent_entry": "2026-04-08 10:30:37 UTC"
      },
      "short": {
        "users": 1,
        "score": 69,
        "earliest_entry": "2026-04-08 10:24:28 UTC",
        "most_recent_entry": "2026-04-08 10:24:28 UTC"
      }
    },
    {
      "rank": 101,
      "coin": "XPL",
      "long": {
        "users": 9,
        "score": 942,
        "earliest_entry": "2026-04-08 10:15:34 UTC",
        "most_recent_entry": "2026-04-08 10:29:52 UTC"
      },
      "short": {
        "users": 2,
        "score": 186,
        "earliest_entry": "2026-04-08 10:17:43 UTC",
        "most_recent_entry": "2026-04-08 10:27:39 UTC"
      }
    },
    {
      "rank": 102,
      "coin": "XRP",
      "long": {
        "users": 8,
        "score": 819,
        "earliest_entry": "2026-04-08 10:15:40 UTC",
        "most_recent_entry": "2026-04-08 10:29:19 UTC"
      },
      "short": {
        "users": 2,
        "score": 117,
        "earliest_entry": "2026-04-08 10:24:28 UTC",
        "most_recent_entry": "2026-04-08 10:29:24 UTC"
      }
    },
    {
      "rank": 103,
      "coin": "ZEC",
      "long": {
        "users": 47,
        "score": 5246,
        "earliest_entry": "2026-04-08 10:15:21 UTC",
        "most_recent_entry": "2026-04-08 10:30:37 UTC"
      },
      "short": {
        "users": 15,
        "score": 1462,
        "earliest_entry": "2026-04-08 10:15:17 UTC",
        "most_recent_entry": "2026-04-08 10:30:15 UTC"
      }
    },
    {
      "rank": 104,
      "coin": "ZEN",
      "long": {
        "users": 1,
        "score": 192,
        "earliest_entry": "2026-04-08 10:16:21 UTC",
        "most_recent_entry": "2026-04-08 10:16:21 UTC"
      },
      "short": {
        "users": 0,
        "score": 0,
        "earliest_entry": null,
        "most_recent_entry": null
      }
    },
    {
      "rank": 105,
      "coin": "ZK",
      "long": {
        "users": 1,
        "score": 45,
        "earliest_entry": "2026-04-08 10:30:37 UTC",
        "most_recent_entry": "2026-04-08 10:30:37 UTC"
      },
      "short": {
        "users": 0,
        "score": 0,
        "earliest_entry": null,
        "most_recent_entry": null
      }
    },
    {
      "rank": 106,
      "coin": "ZRO",
      "long": {
        "users": 5,
        "score": 339,
        "earliest_entry": "2026-04-08 10:19:40 UTC",
        "most_recent_entry": "2026-04-08 10:30:37 UTC"
      },
      "short": {
        "users": 2,
        "score": 137,
        "earliest_entry": "2026-04-08 10:20:23 UTC",
        "most_recent_entry": "2026-04-08 10:29:32 UTC"
      }
    },
    {
      "rank": 107,
      "coin": "kBONK",
      "long": {
        "users": 2,
        "score": 112,
        "earliest_entry": "2026-04-08 10:24:43 UTC",
        "most_recent_entry": "2026-04-08 10:30:37 UTC"
      },
      "short": {
        "users": 1,
        "score": 60,
        "earliest_entry": "2026-04-08 10:26:35 UTC",
        "most_recent_entry": "2026-04-08 10:26:35 UTC"
      }
    },
    {
      "rank": 108,
      "coin": "kPEPE",
      "long": {
        "users": 9,
        "score": 948,
        "earliest_entry": "2026-04-08 10:15:10 UTC",
        "most_recent_entry": "2026-04-08 10:30:37 UTC"
      },
      "short": {
        "users": 1,
        "score": 60,
        "earliest_entry": "2026-04-08 10:26:35 UTC",
        "most_recent_entry": "2026-04-08 10:26:35 UTC"
      }
    },
    {
      "rank": 109,
      "coin": "kSHIB",
      "long": {
        "users": 1,
        "score": 69,
        "earliest_entry": "2026-04-08 10:24:28 UTC",
        "most_recent_entry": "2026-04-08 10:24:28 UTC"
      },
      "short": {
        "users": 3,
        "score": 207,
        "earliest_entry": "2026-04-08 10:20:23 UTC",
        "most_recent_entry": "2026-04-08 10:26:59 UTC"
      }
    }
  ]
}